{
  "title": "JsonFactory",
  "description": "AssetFactory implementation that parses JSON files and exposes them as plain JavaScript values. The parsed value is typed as `unknown`; callers are expected to narrow or cast the result to their specific schema type.",
  "symbol": "JsonFactory",
  "kind": "class",
  "subsystem": "resources",
  "importPath": "@codexo/exojs",
  "tier": "stable",
  "memberCount": 7,
  "counts": {
    "constructors": 1,
    "methods": 5,
    "properties": 1,
    "events": 0
  },
  "sections": [
    {
      "id": "import",
      "title": "Import",
      "members": [],
      "paragraphs": [
        "AssetFactory implementation that parses JSON files and exposes them as plain JavaScript values.",
        "The parsed value is typed as `unknown`; callers are expected to narrow or cast the result to their specific schema type."
      ],
      "importLine": "import { JsonFactory } from '@codexo/exojs'",
      "sourceLink": null
    },
    {
      "id": "constructors",
      "title": "Constructors",
      "members": [
        {
          "name": "new",
          "signature": "new(): JsonFactory",
          "signatureTokens": [
            {
              "text": "new",
              "kind": "keyword"
            },
            {
              "text": "(",
              "kind": "punctuation"
            },
            {
              "text": ")",
              "kind": "punctuation"
            },
            {
              "text": ": ",
              "kind": "punctuation"
            },
            {
              "text": "JsonFactory",
              "kind": "type"
            }
          ],
          "params": [],
          "returnType": "JsonFactory",
          "description": ""
        }
      ],
      "paragraphs": [],
      "importLine": null,
      "sourceLink": null
    },
    {
      "id": "methods",
      "title": "Methods",
      "members": [
        {
          "name": "create",
          "signature": "create(source: unknown): Promise<unknown>",
          "signatureTokens": [
            {
              "text": "create",
              "kind": "name"
            },
            {
              "text": "(",
              "kind": "punctuation"
            },
            {
              "text": "source",
              "kind": "param"
            },
            {
              "text": ": ",
              "kind": "punctuation"
            },
            {
              "text": "unknown",
              "kind": "keyword"
            },
            {
              "text": ")",
              "kind": "punctuation"
            },
            {
              "text": ": ",
              "kind": "punctuation"
            },
            {
              "text": "Promise",
              "kind": "type"
            },
            {
              "text": "<",
              "kind": "punctuation"
            },
            {
              "text": "unknown",
              "kind": "keyword"
            },
            {
              "text": ">",
              "kind": "punctuation"
            }
          ],
          "params": [
            {
              "name": "source",
              "type": "unknown",
              "optional": false
            }
          ],
          "returnType": "Promise<unknown>",
          "description": "Returns the already-parsed value unchanged."
        },
        {
          "name": "createObjectUrl",
          "signature": "createObjectUrl(blob: Blob): string",
          "signatureTokens": [
            {
              "text": "createObjectUrl",
              "kind": "name"
            },
            {
              "text": "(",
              "kind": "punctuation"
            },
            {
              "text": "blob",
              "kind": "param"
            },
            {
              "text": ": ",
              "kind": "punctuation"
            },
            {
              "text": "Blob",
              "kind": "type"
            },
            {
              "text": ")",
              "kind": "punctuation"
            },
            {
              "text": ": ",
              "kind": "punctuation"
            },
            {
              "text": "string",
              "kind": "keyword"
            }
          ],
          "params": [
            {
              "name": "blob",
              "type": "Blob",
              "optional": false
            }
          ],
          "returnType": "string",
          "description": "Creates an object URL from blob and registers it for automatic cleanup when destroy is called. Prefer this over calling URL.createObjectURL directly inside a factory subclass so the URL is always tracked."
        },
        {
          "name": "destroy",
          "signature": "destroy(): void",
          "signatureTokens": [
            {
              "text": "destroy",
              "kind": "name"
            },
            {
              "text": "(",
              "kind": "punctuation"
            },
            {
              "text": ")",
              "kind": "punctuation"
            },
            {
              "text": ": ",
              "kind": "punctuation"
            },
            {
              "text": "void",
              "kind": "keyword"
            }
          ],
          "params": [],
          "returnType": "void",
          "description": "Revokes every object URL that was created via createObjectUrl and clears the internal tracking pool."
        },
        {
          "name": "process",
          "signature": "process(response: Response): Promise<unknown>",
          "signatureTokens": [
            {
              "text": "process",
              "kind": "name"
            },
            {
              "text": "(",
              "kind": "punctuation"
            },
            {
              "text": "response",
              "kind": "param"
            },
            {
              "text": ": ",
              "kind": "punctuation"
            },
            {
              "text": "Response",
              "kind": "type"
            },
            {
              "text": ")",
              "kind": "punctuation"
            },
            {
              "text": ": ",
              "kind": "punctuation"
            },
            {
              "text": "Promise",
              "kind": "type"
            },
            {
              "text": "<",
              "kind": "punctuation"
            },
            {
              "text": "unknown",
              "kind": "keyword"
            },
            {
              "text": ">",
              "kind": "punctuation"
            }
          ],
          "params": [
            {
              "name": "response",
              "type": "Response",
              "optional": false
            }
          ],
          "returnType": "Promise<unknown>",
          "description": "Parses the response body as JSON and returns the resulting value."
        },
        {
          "name": "revokeObjectUrl",
          "signature": "revokeObjectUrl(objectUrl: string): void",
          "signatureTokens": [
            {
              "text": "revokeObjectUrl",
              "kind": "name"
            },
            {
              "text": "(",
              "kind": "punctuation"
            },
            {
              "text": "objectUrl",
              "kind": "param"
            },
            {
              "text": ": ",
              "kind": "punctuation"
            },
            {
              "text": "string",
              "kind": "keyword"
            },
            {
              "text": ")",
              "kind": "punctuation"
            },
            {
              "text": ": ",
              "kind": "punctuation"
            },
            {
              "text": "void",
              "kind": "keyword"
            }
          ],
          "params": [
            {
              "name": "objectUrl",
              "type": "string",
              "optional": false
            }
          ],
          "returnType": "void",
          "description": ""
        }
      ],
      "paragraphs": [],
      "importLine": null,
      "sourceLink": null
    },
    {
      "id": "properties",
      "title": "Properties",
      "members": [
        {
          "name": "storageName",
          "signature": "storageName: \"json\"",
          "signatureTokens": [
            {
              "text": "storageName",
              "kind": "name"
            },
            {
              "text": ": ",
              "kind": "punctuation"
            },
            {
              "text": "\"json\"",
              "kind": "keyword"
            }
          ],
          "params": [],
          "returnType": null,
          "description": "Identifier used as the object-store / storage-namespace key when this factory's assets are persisted to a CacheStore."
        }
      ],
      "paragraphs": [],
      "importLine": null,
      "sourceLink": null
    },
    {
      "id": "source",
      "title": "Source",
      "members": [],
      "paragraphs": [],
      "importLine": null,
      "sourceLink": {
        "label": "src/resources/factories/JsonFactory.ts",
        "href": "https://github.com/Exoridus/ExoJS/blob/main/src/resources/factories/JsonFactory.ts"
      }
    }
  ],
  "sourcePath": "src/resources/factories/JsonFactory.ts",
  "sourceUrl": "https://github.com/Exoridus/ExoJS/blob/main/src/resources/factories/JsonFactory.ts"
}
