{
  "title": "SoundOptions",
  "description": "Construction options for Sound.",
  "symbol": "SoundOptions",
  "kind": "interface",
  "subsystem": "audio",
  "importPath": "@codexo/exojs",
  "tier": "stable",
  "memberCount": 12,
  "counts": {
    "constructors": 0,
    "methods": 0,
    "properties": 12,
    "events": 0
  },
  "sections": [
    {
      "id": "import",
      "title": "Import",
      "members": [],
      "paragraphs": [
        "Construction options for Sound."
      ],
      "importLine": "import { SoundOptions } from '@codexo/exojs'",
      "sourceLink": null
    },
    {
      "id": "properties",
      "title": "Properties",
      "members": [
        {
          "name": "distanceModel",
          "signature": "distanceModel?: DistanceModel",
          "signatureTokens": [
            {
              "text": "distanceModel",
              "kind": "name"
            },
            {
              "text": "?",
              "kind": "punctuation"
            },
            {
              "text": ": ",
              "kind": "punctuation"
            },
            {
              "text": "DistanceModel",
              "kind": "type"
            }
          ],
          "params": [],
          "returnType": null,
          "description": "Distance-attenuation model. Default: 'linear'."
        },
        {
          "name": "loop",
          "signature": "loop?: boolean",
          "signatureTokens": [
            {
              "text": "loop",
              "kind": "name"
            },
            {
              "text": "?",
              "kind": "punctuation"
            },
            {
              "text": ": ",
              "kind": "punctuation"
            },
            {
              "text": "boolean",
              "kind": "keyword"
            }
          ],
          "params": [],
          "returnType": null,
          "description": "Default loop setting. Default: false."
        },
        {
          "name": "maxDistance",
          "signature": "maxDistance?: number",
          "signatureTokens": [
            {
              "text": "maxDistance",
              "kind": "name"
            },
            {
              "text": "?",
              "kind": "punctuation"
            },
            {
              "text": ": ",
              "kind": "punctuation"
            },
            {
              "text": "number",
              "kind": "keyword"
            }
          ],
          "params": [],
          "returnType": null,
          "description": "For the 'linear' model: distance at which volume reaches zero. Default: 1000."
        },
        {
          "name": "muted",
          "signature": "muted?: boolean",
          "signatureTokens": [
            {
              "text": "muted",
              "kind": "name"
            },
            {
              "text": "?",
              "kind": "punctuation"
            },
            {
              "text": ": ",
              "kind": "punctuation"
            },
            {
              "text": "boolean",
              "kind": "keyword"
            }
          ],
          "params": [],
          "returnType": null,
          "description": "Default muted state. Default: false."
        },
        {
          "name": "playbackRate",
          "signature": "playbackRate?: number",
          "signatureTokens": [
            {
              "text": "playbackRate",
              "kind": "name"
            },
            {
              "text": "?",
              "kind": "punctuation"
            },
            {
              "text": ": ",
              "kind": "punctuation"
            },
            {
              "text": "number",
              "kind": "keyword"
            }
          ],
          "params": [],
          "returnType": null,
          "description": "Default playback rate. Default: 1."
        },
        {
          "name": "poolSize",
          "signature": "poolSize?: number",
          "signatureTokens": [
            {
              "text": "poolSize",
              "kind": "name"
            },
            {
              "text": "?",
              "kind": "punctuation"
            },
            {
              "text": ": ",
              "kind": "punctuation"
            },
            {
              "text": "number",
              "kind": "keyword"
            }
          ],
          "params": [],
          "returnType": null,
          "description": ""
        },
        {
          "name": "poolStrategy",
          "signature": "poolStrategy?: SoundPoolStrategy",
          "signatureTokens": [
            {
              "text": "poolStrategy",
              "kind": "name"
            },
            {
              "text": "?",
              "kind": "punctuation"
            },
            {
              "text": ": ",
              "kind": "punctuation"
            },
            {
              "text": "SoundPoolStrategy",
              "kind": "type"
            }
          ],
          "params": [],
          "returnType": null,
          "description": ""
        },
        {
          "name": "priority",
          "signature": "priority?: number",
          "signatureTokens": [
            {
              "text": "priority",
              "kind": "name"
            },
            {
              "text": "?",
              "kind": "punctuation"
            },
            {
              "text": ": ",
              "kind": "punctuation"
            },
            {
              "text": "number",
              "kind": "keyword"
            }
          ],
          "params": [],
          "returnType": null,
          "description": ""
        },
        {
          "name": "refDistance",
          "signature": "refDistance?: number",
          "signatureTokens": [
            {
              "text": "refDistance",
              "kind": "name"
            },
            {
              "text": "?",
              "kind": "punctuation"
            },
            {
              "text": ": ",
              "kind": "punctuation"
            },
            {
              "text": "number",
              "kind": "keyword"
            }
          ],
          "params": [],
          "returnType": null,
          "description": "Distance below which volume is at full strength. Default: 50."
        },
        {
          "name": "rolloffFactor",
          "signature": "rolloffFactor?: number",
          "signatureTokens": [
            {
              "text": "rolloffFactor",
              "kind": "name"
            },
            {
              "text": "?",
              "kind": "punctuation"
            },
            {
              "text": ": ",
              "kind": "punctuation"
            },
            {
              "text": "number",
              "kind": "keyword"
            }
          ],
          "params": [],
          "returnType": null,
          "description": "Falloff rate. Higher = steeper attenuation. Default: 1."
        },
        {
          "name": "sprites",
          "signature": "sprites?: Readonly<Record<string, AudioSpriteClip>>",
          "signatureTokens": [
            {
              "text": "sprites",
              "kind": "name"
            },
            {
              "text": "?",
              "kind": "punctuation"
            },
            {
              "text": ": ",
              "kind": "punctuation"
            },
            {
              "text": "Readonly",
              "kind": "type"
            },
            {
              "text": "<",
              "kind": "punctuation"
            },
            {
              "text": "Record",
              "kind": "type"
            },
            {
              "text": "<",
              "kind": "punctuation"
            },
            {
              "text": "string",
              "kind": "keyword"
            },
            {
              "text": ", ",
              "kind": "punctuation"
            },
            {
              "text": "AudioSpriteClip",
              "kind": "type"
            },
            {
              "text": ">",
              "kind": "punctuation"
            },
            {
              "text": ">",
              "kind": "punctuation"
            }
          ],
          "params": [],
          "returnType": null,
          "description": ""
        },
        {
          "name": "volume",
          "signature": "volume?: number",
          "signatureTokens": [
            {
              "text": "volume",
              "kind": "name"
            },
            {
              "text": "?",
              "kind": "punctuation"
            },
            {
              "text": ": ",
              "kind": "punctuation"
            },
            {
              "text": "number",
              "kind": "keyword"
            }
          ],
          "params": [],
          "returnType": null,
          "description": "Default volume for voices created from this sound. Range [0, 1]. Default: 1."
        }
      ],
      "paragraphs": [],
      "importLine": null,
      "sourceLink": null
    },
    {
      "id": "source",
      "title": "Source",
      "members": [],
      "paragraphs": [],
      "importLine": null,
      "sourceLink": {
        "label": "src/audio/Sound.ts",
        "href": "https://github.com/Exoridus/ExoJS/blob/main/src/audio/Sound.ts"
      }
    }
  ],
  "sourcePath": "src/audio/Sound.ts",
  "sourceUrl": "https://github.com/Exoridus/ExoJS/blob/main/src/audio/Sound.ts"
}
