{
  "title": "TiledTileLayerData",
  "description": "A finite-map tile layer has `data` (a flat, row-major array of GIDs of length `width * height`). An infinite-map tile layer has `chunks` instead.",
  "symbol": "TiledTileLayerData",
  "kind": "interface",
  "subsystem": "tiled",
  "importPath": "@codexo/exojs-tiled",
  "tier": "stable",
  "memberCount": 18,
  "counts": {
    "constructors": 0,
    "methods": 0,
    "properties": 18,
    "events": 0
  },
  "sections": [
    {
      "id": "import",
      "title": "Import",
      "members": [],
      "paragraphs": [
        "A finite-map tile layer has `data` (a flat, row-major array of GIDs of length `width * height`). An infinite-map tile layer has `chunks` instead."
      ],
      "importLine": "import { TiledTileLayerData } from '@codexo/exojs-tiled'",
      "sourceLink": null
    },
    {
      "id": "properties",
      "title": "Properties",
      "members": [
        {
          "name": "chunks",
          "signature": "chunks?: readonly TiledChunkData[]",
          "signatureTokens": [
            {
              "text": "chunks",
              "kind": "name"
            },
            {
              "text": "?",
              "kind": "punctuation"
            },
            {
              "text": ": ",
              "kind": "punctuation"
            },
            {
              "text": "readonly",
              "kind": "keyword"
            },
            {
              "text": " ",
              "kind": "punctuation"
            },
            {
              "text": "TiledChunkData",
              "kind": "type"
            },
            {
              "text": "[]",
              "kind": "punctuation"
            }
          ],
          "params": [],
          "returnType": null,
          "description": ""
        },
        {
          "name": "class",
          "signature": "class?: string",
          "signatureTokens": [
            {
              "text": "class",
              "kind": "name"
            },
            {
              "text": "?",
              "kind": "punctuation"
            },
            {
              "text": ": ",
              "kind": "punctuation"
            },
            {
              "text": "string",
              "kind": "keyword"
            }
          ],
          "params": [],
          "returnType": null,
          "description": ""
        },
        {
          "name": "data",
          "signature": "data?: readonly number[]",
          "signatureTokens": [
            {
              "text": "data",
              "kind": "name"
            },
            {
              "text": "?",
              "kind": "punctuation"
            },
            {
              "text": ": ",
              "kind": "punctuation"
            },
            {
              "text": "readonly",
              "kind": "keyword"
            },
            {
              "text": " ",
              "kind": "punctuation"
            },
            {
              "text": "number",
              "kind": "keyword"
            },
            {
              "text": "[]",
              "kind": "punctuation"
            }
          ],
          "params": [],
          "returnType": null,
          "description": ""
        },
        {
          "name": "height",
          "signature": "height: number",
          "signatureTokens": [
            {
              "text": "height",
              "kind": "name"
            },
            {
              "text": ": ",
              "kind": "punctuation"
            },
            {
              "text": "number",
              "kind": "keyword"
            }
          ],
          "params": [],
          "returnType": null,
          "description": ""
        },
        {
          "name": "id",
          "signature": "id: number",
          "signatureTokens": [
            {
              "text": "id",
              "kind": "name"
            },
            {
              "text": ": ",
              "kind": "punctuation"
            },
            {
              "text": "number",
              "kind": "keyword"
            }
          ],
          "params": [],
          "returnType": null,
          "description": ""
        },
        {
          "name": "name",
          "signature": "name: string",
          "signatureTokens": [
            {
              "text": "name",
              "kind": "name"
            },
            {
              "text": ": ",
              "kind": "punctuation"
            },
            {
              "text": "string",
              "kind": "keyword"
            }
          ],
          "params": [],
          "returnType": null,
          "description": ""
        },
        {
          "name": "offsetx",
          "signature": "offsetx?: number",
          "signatureTokens": [
            {
              "text": "offsetx",
              "kind": "name"
            },
            {
              "text": "?",
              "kind": "punctuation"
            },
            {
              "text": ": ",
              "kind": "punctuation"
            },
            {
              "text": "number",
              "kind": "keyword"
            }
          ],
          "params": [],
          "returnType": null,
          "description": ""
        },
        {
          "name": "offsety",
          "signature": "offsety?: number",
          "signatureTokens": [
            {
              "text": "offsety",
              "kind": "name"
            },
            {
              "text": "?",
              "kind": "punctuation"
            },
            {
              "text": ": ",
              "kind": "punctuation"
            },
            {
              "text": "number",
              "kind": "keyword"
            }
          ],
          "params": [],
          "returnType": null,
          "description": ""
        },
        {
          "name": "opacity",
          "signature": "opacity: number",
          "signatureTokens": [
            {
              "text": "opacity",
              "kind": "name"
            },
            {
              "text": ": ",
              "kind": "punctuation"
            },
            {
              "text": "number",
              "kind": "keyword"
            }
          ],
          "params": [],
          "returnType": null,
          "description": ""
        },
        {
          "name": "parallaxx",
          "signature": "parallaxx?: number",
          "signatureTokens": [
            {
              "text": "parallaxx",
              "kind": "name"
            },
            {
              "text": "?",
              "kind": "punctuation"
            },
            {
              "text": ": ",
              "kind": "punctuation"
            },
            {
              "text": "number",
              "kind": "keyword"
            }
          ],
          "params": [],
          "returnType": null,
          "description": ""
        },
        {
          "name": "parallaxy",
          "signature": "parallaxy?: number",
          "signatureTokens": [
            {
              "text": "parallaxy",
              "kind": "name"
            },
            {
              "text": "?",
              "kind": "punctuation"
            },
            {
              "text": ": ",
              "kind": "punctuation"
            },
            {
              "text": "number",
              "kind": "keyword"
            }
          ],
          "params": [],
          "returnType": null,
          "description": ""
        },
        {
          "name": "properties",
          "signature": "properties?: readonly TiledPropertyData[]",
          "signatureTokens": [
            {
              "text": "properties",
              "kind": "name"
            },
            {
              "text": "?",
              "kind": "punctuation"
            },
            {
              "text": ": ",
              "kind": "punctuation"
            },
            {
              "text": "readonly",
              "kind": "keyword"
            },
            {
              "text": " ",
              "kind": "punctuation"
            },
            {
              "text": "TiledPropertyData",
              "kind": "type"
            },
            {
              "text": "[]",
              "kind": "punctuation"
            }
          ],
          "params": [],
          "returnType": null,
          "description": ""
        },
        {
          "name": "tintcolor",
          "signature": "tintcolor?: string",
          "signatureTokens": [
            {
              "text": "tintcolor",
              "kind": "name"
            },
            {
              "text": "?",
              "kind": "punctuation"
            },
            {
              "text": ": ",
              "kind": "punctuation"
            },
            {
              "text": "string",
              "kind": "keyword"
            }
          ],
          "params": [],
          "returnType": null,
          "description": ""
        },
        {
          "name": "type",
          "signature": "type: \"tilelayer\"",
          "signatureTokens": [
            {
              "text": "type",
              "kind": "name"
            },
            {
              "text": ": ",
              "kind": "punctuation"
            },
            {
              "text": "\"tilelayer\"",
              "kind": "keyword"
            }
          ],
          "params": [],
          "returnType": null,
          "description": ""
        },
        {
          "name": "visible",
          "signature": "visible: boolean",
          "signatureTokens": [
            {
              "text": "visible",
              "kind": "name"
            },
            {
              "text": ": ",
              "kind": "punctuation"
            },
            {
              "text": "boolean",
              "kind": "keyword"
            }
          ],
          "params": [],
          "returnType": null,
          "description": ""
        },
        {
          "name": "width",
          "signature": "width: number",
          "signatureTokens": [
            {
              "text": "width",
              "kind": "name"
            },
            {
              "text": ": ",
              "kind": "punctuation"
            },
            {
              "text": "number",
              "kind": "keyword"
            }
          ],
          "params": [],
          "returnType": null,
          "description": ""
        },
        {
          "name": "x",
          "signature": "x: number",
          "signatureTokens": [
            {
              "text": "x",
              "kind": "name"
            },
            {
              "text": ": ",
              "kind": "punctuation"
            },
            {
              "text": "number",
              "kind": "keyword"
            }
          ],
          "params": [],
          "returnType": null,
          "description": ""
        },
        {
          "name": "y",
          "signature": "y: number",
          "signatureTokens": [
            {
              "text": "y",
              "kind": "name"
            },
            {
              "text": ": ",
              "kind": "punctuation"
            },
            {
              "text": "number",
              "kind": "keyword"
            }
          ],
          "params": [],
          "returnType": null,
          "description": ""
        }
      ],
      "paragraphs": [],
      "importLine": null,
      "sourceLink": null
    },
    {
      "id": "source",
      "title": "Source",
      "members": [],
      "paragraphs": [],
      "importLine": null,
      "sourceLink": {
        "label": "packages/exojs-tiled/src/data.ts",
        "href": "https://github.com/Exoridus/ExoJS/blob/main/packages/exojs-tiled/src/data.ts"
      }
    }
  ],
  "sourcePath": "packages/exojs-tiled/src/data.ts",
  "sourceUrl": "https://github.com/Exoridus/ExoJS/blob/main/packages/exojs-tiled/src/data.ts"
}
