{
  "title": "TileMapOptions",
  "description": "Options for constructing a TileMap.",
  "symbol": "TileMapOptions",
  "kind": "interface",
  "subsystem": "tilemap",
  "importPath": "@codexo/exojs-tilemap",
  "tier": "advanced",
  "memberCount": 16,
  "counts": {
    "constructors": 0,
    "methods": 0,
    "properties": 16,
    "events": 0
  },
  "sections": [
    {
      "id": "import",
      "title": "Import",
      "members": [],
      "paragraphs": [
        "Options for constructing a TileMap."
      ],
      "importLine": "import { TileMapOptions } from '@codexo/exojs-tilemap'",
      "sourceLink": null
    },
    {
      "id": "properties",
      "title": "Properties",
      "members": [
        {
          "name": "backgroundColor",
          "signature": "backgroundColor?: number | null",
          "signatureTokens": [
            {
              "text": "backgroundColor",
              "kind": "name"
            },
            {
              "text": "?",
              "kind": "punctuation"
            },
            {
              "text": ": ",
              "kind": "punctuation"
            },
            {
              "text": "number",
              "kind": "keyword"
            },
            {
              "text": " | ",
              "kind": "punctuation"
            },
            {
              "text": "null",
              "kind": "keyword"
            }
          ],
          "params": [],
          "returnType": null,
          "description": "Map background colour as a 0xRRGGBB integer, or null (Tiled backgroundcolor). Informational — the renderer does not auto-clear to it. Default null."
        },
        {
          "name": "chunkHeight",
          "signature": "chunkHeight?: number",
          "signatureTokens": [
            {
              "text": "chunkHeight",
              "kind": "name"
            },
            {
              "text": "?",
              "kind": "punctuation"
            },
            {
              "text": ": ",
              "kind": "punctuation"
            },
            {
              "text": "number",
              "kind": "keyword"
            }
          ],
          "params": [],
          "returnType": null,
          "description": "Chunk height for layers (default 32)."
        },
        {
          "name": "chunkWidth",
          "signature": "chunkWidth?: number",
          "signatureTokens": [
            {
              "text": "chunkWidth",
              "kind": "name"
            },
            {
              "text": "?",
              "kind": "punctuation"
            },
            {
              "text": ": ",
              "kind": "punctuation"
            },
            {
              "text": "number",
              "kind": "keyword"
            }
          ],
          "params": [],
          "returnType": null,
          "description": "Chunk width for layers (default 32)."
        },
        {
          "name": "class",
          "signature": "class?: string",
          "signatureTokens": [
            {
              "text": "class",
              "kind": "name"
            },
            {
              "text": "?",
              "kind": "punctuation"
            },
            {
              "text": ": ",
              "kind": "punctuation"
            },
            {
              "text": "string",
              "kind": "keyword"
            }
          ],
          "params": [],
          "returnType": null,
          "description": "Map class/type string (Tiled class). Defaults to ''."
        },
        {
          "name": "documentOrder",
          "signature": "documentOrder?: readonly number[]",
          "signatureTokens": [
            {
              "text": "documentOrder",
              "kind": "name"
            },
            {
              "text": "?",
              "kind": "punctuation"
            },
            {
              "text": ": ",
              "kind": "punctuation"
            },
            {
              "text": "readonly",
              "kind": "keyword"
            },
            {
              "text": " ",
              "kind": "punctuation"
            },
            {
              "text": "number",
              "kind": "keyword"
            },
            {
              "text": "[]",
              "kind": "punctuation"
            }
          ],
          "params": [],
          "returnType": null,
          "description": "Combined document order across tile and image layers, as an ordered list of layer ids — exposed via TileMap.renderableLayers. Every tile and image layer passed to this map (via layers / imageLayers) must appear exactly once; an id that belongs to neither kind, or is listed more than once, throws. The list's length must also equal the total number of tile/image layer instances — nothing enforces unique ids across image layers, so two image layers sharing an id would otherwise both satisfy the id-based checks while one silently drops out of TileMap.renderableLayers; that mismatch throws too. A tile layer and an image layer sharing the same id makes the order ambiguous — that combination throws when documentOrder is provided. It is NOT rejected when this option is omitted: the fallback order below is unambiguous by construction (tile layers are always listed before image layers), so hand-built maps that predate this option are unaffected even if such an id collision exists. Omit to fall back to all tile layers in insertion order, followed by all image layers in insertion order — the map's implicit ordering before this option existed. Named documentOrder rather than renderOrder to avoid colliding with the unrelated renderOrder option above (Tiled's tile-draw- direction string, e.g. 'right-down')."
        },
        {
          "name": "height",
          "signature": "height?: number",
          "signatureTokens": [
            {
              "text": "height",
              "kind": "name"
            },
            {
              "text": "?",
              "kind": "punctuation"
            },
            {
              "text": ": ",
              "kind": "punctuation"
            },
            {
              "text": "number",
              "kind": "keyword"
            }
          ],
          "params": [],
          "returnType": null,
          "description": "Map height in tiles. Must be provided iff width is."
        },
        {
          "name": "imageLayers",
          "signature": "imageLayers?: readonly ImageLayer[]",
          "signatureTokens": [
            {
              "text": "imageLayers",
              "kind": "name"
            },
            {
              "text": "?",
              "kind": "punctuation"
            },
            {
              "text": ": ",
              "kind": "punctuation"
            },
            {
              "text": "readonly",
              "kind": "keyword"
            },
            {
              "text": " ",
              "kind": "punctuation"
            },
            {
              "text": "ImageLayer",
              "kind": "type"
            },
            {
              "text": "[]",
              "kind": "punctuation"
            }
          ],
          "params": [],
          "returnType": null,
          "description": "Image layers (data-only; background/foreground images from Tiled image layers)."
        },
        {
          "name": "layers",
          "signature": "layers?: readonly TileLayer[]",
          "signatureTokens": [
            {
              "text": "layers",
              "kind": "name"
            },
            {
              "text": "?",
              "kind": "punctuation"
            },
            {
              "text": ": ",
              "kind": "punctuation"
            },
            {
              "text": "readonly",
              "kind": "keyword"
            },
            {
              "text": " ",
              "kind": "punctuation"
            },
            {
              "text": "TileLayer",
              "kind": "type"
            },
            {
              "text": "[]",
              "kind": "punctuation"
            }
          ],
          "params": [],
          "returnType": null,
          "description": "Layers (constructed externally and owned by the map after construction)."
        },
        {
          "name": "name",
          "signature": "name?: string",
          "signatureTokens": [
            {
              "text": "name",
              "kind": "name"
            },
            {
              "text": "?",
              "kind": "punctuation"
            },
            {
              "text": ": ",
              "kind": "punctuation"
            },
            {
              "text": "string",
              "kind": "keyword"
            }
          ],
          "params": [],
          "returnType": null,
          "description": "Map name (for debugging)."
        },
        {
          "name": "objectLayers",
          "signature": "objectLayers?: readonly ObjectLayer<ObjectSchema>[]",
          "signatureTokens": [
            {
              "text": "objectLayers",
              "kind": "name"
            },
            {
              "text": "?",
              "kind": "punctuation"
            },
            {
              "text": ": ",
              "kind": "punctuation"
            },
            {
              "text": "readonly",
              "kind": "keyword"
            },
            {
              "text": " ",
              "kind": "punctuation"
            },
            {
              "text": "ObjectLayer",
              "kind": "type"
            },
            {
              "text": "<",
              "kind": "punctuation"
            },
            {
              "text": "ObjectSchema",
              "kind": "type"
            },
            {
              "text": ">",
              "kind": "punctuation"
            },
            {
              "text": "[]",
              "kind": "punctuation"
            }
          ],
          "params": [],
          "returnType": null,
          "description": "Object layers (data-only; spawn points, triggers, collision regions)."
        },
        {
          "name": "properties",
          "signature": "properties?: TileProperties",
          "signatureTokens": [
            {
              "text": "properties",
              "kind": "name"
            },
            {
              "text": "?",
              "kind": "punctuation"
            },
            {
              "text": ": ",
              "kind": "punctuation"
            },
            {
              "text": "TileProperties",
              "kind": "type"
            }
          ],
          "params": [],
          "returnType": null,
          "description": "Map-level properties (copied and frozen)."
        },
        {
          "name": "renderOrder",
          "signature": "renderOrder?: string",
          "signatureTokens": [
            {
              "text": "renderOrder",
              "kind": "name"
            },
            {
              "text": "?",
              "kind": "punctuation"
            },
            {
              "text": ": ",
              "kind": "punctuation"
            },
            {
              "text": "string",
              "kind": "keyword"
            }
          ],
          "params": [],
          "returnType": null,
          "description": "Tile draw order (Tiled renderorder), informational. Default 'right-down'."
        },
        {
          "name": "tileHeight",
          "signature": "tileHeight: number",
          "signatureTokens": [
            {
              "text": "tileHeight",
              "kind": "name"
            },
            {
              "text": ": ",
              "kind": "punctuation"
            },
            {
              "text": "number",
              "kind": "keyword"
            }
          ],
          "params": [],
          "returnType": null,
          "description": "Height of each tile in pixels."
        },
        {
          "name": "tilesets",
          "signature": "tilesets?: readonly TileSet[]",
          "signatureTokens": [
            {
              "text": "tilesets",
              "kind": "name"
            },
            {
              "text": "?",
              "kind": "punctuation"
            },
            {
              "text": ": ",
              "kind": "punctuation"
            },
            {
              "text": "readonly",
              "kind": "keyword"
            },
            {
              "text": " ",
              "kind": "punctuation"
            },
            {
              "text": "TileSet",
              "kind": "type"
            },
            {
              "text": "[]",
              "kind": "punctuation"
            }
          ],
          "params": [],
          "returnType": null,
          "description": "Tilesets available to this map."
        },
        {
          "name": "tileWidth",
          "signature": "tileWidth: number",
          "signatureTokens": [
            {
              "text": "tileWidth",
              "kind": "name"
            },
            {
              "text": ": ",
              "kind": "punctuation"
            },
            {
              "text": "number",
              "kind": "keyword"
            }
          ],
          "params": [],
          "returnType": null,
          "description": "Width of each tile in pixels."
        },
        {
          "name": "width",
          "signature": "width?: number",
          "signatureTokens": [
            {
              "text": "width",
              "kind": "name"
            },
            {
              "text": "?",
              "kind": "punctuation"
            },
            {
              "text": ": ",
              "kind": "punctuation"
            },
            {
              "text": "number",
              "kind": "keyword"
            }
          ],
          "params": [],
          "returnType": null,
          "description": "Map width in tiles. Omit together with height for an unbounded map — layers you add are then free to be unbounded too (this option does not constrain per-layer dimensions either way)."
        }
      ],
      "paragraphs": [],
      "importLine": null,
      "sourceLink": null
    },
    {
      "id": "source",
      "title": "Source",
      "members": [],
      "paragraphs": [],
      "importLine": null,
      "sourceLink": {
        "label": "packages/exojs-tilemap/src/TileMap.ts",
        "href": "https://github.com/Exoridus/ExoJS/blob/main/packages/exojs-tilemap/src/TileMap.ts"
      }
    }
  ],
  "sourcePath": "packages/exojs-tilemap/src/TileMap.ts",
  "sourceUrl": "https://github.com/Exoridus/ExoJS/blob/main/packages/exojs-tilemap/src/TileMap.ts"
}
