{
  "title": "TilePropertyValue",
  "description": "Union of legal tile-property value types in the generic runtime. Format-neutral; adapters map their native property systems into this set — including the structured TilePropertyPoint, TilePropertyObjectRef, and TilePropertyTileRef variants, arrays of any of the above, and nested property bags (e.g. Tiled `class`-typed properties).",
  "symbol": "TilePropertyValue",
  "kind": "type",
  "subsystem": "tilemap",
  "importPath": "@codexo/exojs-tilemap",
  "tier": "advanced",
  "memberCount": 0,
  "counts": {
    "constructors": 0,
    "methods": 0,
    "properties": 0,
    "events": 0
  },
  "sections": [
    {
      "id": "import",
      "title": "Import",
      "members": [],
      "paragraphs": [
        "Union of legal tile-property value types in the generic runtime. Format-neutral; adapters map their native property systems into this set — including the structured TilePropertyPoint, TilePropertyObjectRef, and TilePropertyTileRef variants, arrays of any of the above, and nested property bags (e.g. Tiled `class`-typed properties)."
      ],
      "importLine": "import { TilePropertyValue } from '@codexo/exojs-tilemap'",
      "sourceLink": null
    },
    {
      "id": "definition",
      "title": "Definition",
      "members": [
        {
          "name": "TilePropertyValue",
          "signature": "null | boolean | number | string | TilePropertyPoint | TilePropertyObjectRef | TilePropertyTileRef | readonly TilePropertyValue[] | TileProperties",
          "signatureTokens": [
            {
              "text": "null",
              "kind": "keyword"
            },
            {
              "text": " | ",
              "kind": "punctuation"
            },
            {
              "text": "boolean",
              "kind": "keyword"
            },
            {
              "text": " | ",
              "kind": "punctuation"
            },
            {
              "text": "number",
              "kind": "keyword"
            },
            {
              "text": " | ",
              "kind": "punctuation"
            },
            {
              "text": "string",
              "kind": "keyword"
            },
            {
              "text": " | ",
              "kind": "punctuation"
            },
            {
              "text": "TilePropertyPoint",
              "kind": "type"
            },
            {
              "text": " | ",
              "kind": "punctuation"
            },
            {
              "text": "TilePropertyObjectRef",
              "kind": "type"
            },
            {
              "text": " | ",
              "kind": "punctuation"
            },
            {
              "text": "TilePropertyTileRef",
              "kind": "type"
            },
            {
              "text": " | ",
              "kind": "punctuation"
            },
            {
              "text": "readonly",
              "kind": "keyword"
            },
            {
              "text": " ",
              "kind": "punctuation"
            },
            {
              "text": "TilePropertyValue",
              "kind": "type"
            },
            {
              "text": "[]",
              "kind": "punctuation"
            },
            {
              "text": " | ",
              "kind": "punctuation"
            },
            {
              "text": "TileProperties",
              "kind": "type"
            }
          ],
          "params": [],
          "returnType": null,
          "description": ""
        }
      ],
      "paragraphs": [],
      "importLine": null,
      "sourceLink": null
    },
    {
      "id": "source",
      "title": "Source",
      "members": [],
      "paragraphs": [],
      "importLine": null,
      "sourceLink": {
        "label": "packages/exojs-tilemap/src/types.ts",
        "href": "https://github.com/Exoridus/ExoJS/blob/main/packages/exojs-tilemap/src/types.ts"
      }
    }
  ],
  "sourcePath": "packages/exojs-tilemap/src/types.ts",
  "sourceUrl": "https://github.com/Exoridus/ExoJS/blob/main/packages/exojs-tilemap/src/types.ts"
}
